Metadata-Version: 2.4
Name: mkite_core
Version: 25.11.3
Summary: distributed computing for high-throughput materials simulation
Author-email: Daniel Schwalbe-Koda <dskoda@ucla.edu>
License:                                  Apache License
Project-URL: Homepage, https://github.com/mkite-group
Keywords: workflow,materials-science
Requires-Python: >=3.8
License-File: LICENSE
License-File: NOTICE
Requires-Dist: msgspec>=0.14.1
Requires-Dist: click
Requires-Dist: pydantic>=2.0
Requires-Dist: pydantic-settings>=2.0
Requires-Dist: ase
Requires-Dist: pymatgen
Requires-Dist: rdkit
Dynamic: license-file
